TraceRecursio/__init__.py
TraceRecursio/config/__init__.py
TraceRecursio/config/default_graph.css
TraceRecursio/MANIFEST.in
TraceRecursio/tracer.py
tracerecursio-2.1.3.dist-info/LICENSE
tracerecursio-2.1.3.dist-info/METADATA
tracerecursio-2.1.3.dist-info/WHEEL
tracerecursio-2.1.3.dist-info/RECORD
